{"slug":"agrada-te-do-senhor-e-viveras","title":"Agrada-te do Senhor e viverás","content":"<p>Bom dia, na paz do Senhor Jesus. Cristo vive!<br />\\r\\nUma advert&ecirc;ncia do ap&oacute;stolo Paulo, &agrave; igreja que estava em Roma. Se j&aacute; recebemos a Cristo como Senhor e salvador de nossa vida, devemos buscar as coisas que s&atilde;o de cima. N&atilde;o nos inclinarmos para as coisas desse mundo, onde o poder das trevas tem operado. Est&aacute; chegando o carnaval, festa da carne, satan&aacute;s aproveita esse momento e faz uma arrua&ccedil;a, onde vidas s&atilde;o ceifadas. Drogas, sexo, embriagues e muitas outras coisas acontecem nesses dias. Cuidado, permane&ccedil;a na sua posi&ccedil;&atilde;o, coloque a sua vida no altar e viva para Deus. Deixa o Esp&iacute;rito Santo dominar voc&ecirc; e busque as coisas que s&atilde;o de cima. S&oacute; assim, ter&aacute;s uma vida vitoriosa e aben&ccedil;oada.<br />\\r\\nDeus te aben&ccedil;oe hoje e sempre.<br />\\r\\nTenha um dia de paz.<br />\\r\\nAbra&ccedil;os.</p>","citation":"<p>&quot;Porque a inclina&ccedil;&atilde;o da carne &eacute; morte; mas a inclina&ccedil;&atilde;o do Esp&iacute;rito &eacute; vida e paz. Porquanto a inclina&ccedil;&atilde;o da carne &eacute; inimizade contra Deus, pois n&atilde;o &eacute; sujeita &agrave; lei de Deus, nem, em verdade, o pode ser. Portanto, os que est&atilde;o na carne n&atilde;o podem agradar a Deus.&quot;<br />\\r\\n&nbsp;</p>","reference":"Romanos 8:6-8 ARC"}