{"slug":"andando-na-lei-do-senhor","title":"Andando na Lei do Senhor","content":"<p>Boa tarde, povo s&aacute;bio de nosso Senhor Jesus Cristo. Gra&ccedil;a e paz!</p>\\r\\n\\r\\n<p>O texto, retrata a vida do homem que vive uma vida reta diante de Deus. Que anda segundo a vontade do Senhor. &nbsp;Que n&atilde;o se det&eacute;m nos caminhos dos pecadores e n&atilde;o anda na roda dos escarnecedores. &nbsp;Esse homem teme ao Senhor e tem prazer na sua lei, meditando de dia e noite. Isto, o faz ser pr&oacute;spero, aben&ccedil;oado e semelhante &agrave; &aacute;rvore frut&iacute;fera, o qual d&aacute; o seu fruto na esta&ccedil;&atilde;o pr&oacute;pria e cujas folhas n&atilde;o caem. Que coisa linda e maravilhosa. Tudo isso, bastando somente, guardar, meditar e viver a Lei do Senhor. Portanto, n&atilde;o sejas como os&nbsp;&iacute;mpios, &nbsp;cujas as mentes n&atilde;o est&atilde;o no Senhor e s&atilde;o como a moinha que o vento espalha. Eles n&atilde;o subsistir&atilde;o na congrega&ccedil;&atilde;o dos justos. Se queres ser um crente aben&ccedil;oado, tema ao Senhor e ande em conformidade com a sua Palavra.</p>\\r\\n\\r\\n<p>Tenha um dia de vit&oacute;rias.</p>\\r\\n\\r\\n<p>Abra&ccedil;os.</p>","citation":"<p>&ldquo;Bem-aventurado o var&atilde;o que n&atilde;o anda segundo o conselho dos &iacute;mpios, nem se det&eacute;m no caminho dos pecadores, nem se assenta na roda dos escarnecedores. Antes, tem o seu prazer na lei do Senhor, e na sua lei medita de dia e de noite. Pois ser&aacute; como a &aacute;rvore plantada junto a ribeiros de &aacute;guas, a qual d&aacute; o seu fruto na esta&ccedil;&atilde;o pr&oacute;pria, e cujas folhas n&atilde;o caem, e tudo quanto fizer prosperar&aacute;. N&atilde;o s&atilde;o assim os &iacute;mpios; mas s&atilde;o como a moinha que o vento espalha. Pelo que os &iacute;mpios n&atilde;o subsistir&atilde;o no ju&iacute;zo, nem os pecadores na congrega&ccedil;&atilde;o dos justos. Porque o Senhor conhece o caminho dos justos; mas o caminho dos &iacute;mpios perecer&aacute;.&rdquo;</p>\\r\\n\\r\\n<p>‭‭</p>","reference":"Salmos‬ ‭1:1-6‬ ‭ARC‬‬"}