{"slug":"esperando-em-deus","title":"Esperando em Deus","content":"<p>Bom dia, povo bendito do Rei Eterno.<br />\\r\\n&quot;Assim como o cervo brama pelas correntes de &aacute;gua, assim a minha suspira por ti &oacute; Deus.&quot; Sl 42.1.<br />\\r\\nO salmista anela pelo Senhor, anseia pelo Deus eterno. Deseja ter o Senhor consigo, em todos os momentos da sua vida. Isso &eacute; muito lindo, &eacute; algo maravilhoso, querer sentir Deus no seu ser. Imagina um seguran&ccedil;a, que passa&nbsp;uma noite inteira, sozinho, num lugar deserto, mas, precisa estar&nbsp;ali, de prontid&atilde;o. Como ele deve suspirar, para que o dia chegue logo e a noite passe como um rel&acirc;mpago. Assim, precisamos n&oacute;s ansiar por Deus. N&atilde;o podemos querer Deus, somente nos momentos ruins de nossa vida. Temos que sentir esta necessidade em todos os instantes de nosso viver. N&atilde;o sejamos hip&oacute;critas, sejamos verdadeiros. Por isso te digo, ponha a sua esperan&ccedil;a no Senhor e seja sol&iacute;cito. N&atilde;o olhes para tr&aacute;s, mas busque a Deus com fervor e determina&ccedil;&atilde;o. Quer milagre? Suspire por Deus. Quer Vitoria? Ore com f&eacute;. Certamente Deus vir&aacute; te socorrer. Creia e receba a tua vit&oacute;ria, em nome de Jesus.<br />\\r\\nTenha um dia de milagres.<br />\\r\\nAbra&ccedil;os.</p>","citation":"<p>&ldquo;Espero no Senhor com todo o meu ser e na sua palavra ponho a minha esperan&ccedil;a. Espero pelo Senhor mais do que as sentinelas pela manh&atilde;; sim, mais do que as sentinelas esperam pela manh&atilde;! Ponha a sua esperan&ccedil;a no Senhor, &oacute; Israel, pois no Senhor h&aacute; amor leal e plena reden&ccedil;&atilde;o.&rdquo;</p>","reference":"Salmos‬ ‭130:5-7‬ ‭NVI‬."}