{"slug":"graca-salvadora","title":"A Graça Salvadora","content":"<p>Bom dia, na paz do Senhor Jesus Cristo!</p>\\r\\n\\r\\n<p>Que texto glorioso o ap&oacute;stolo dos gentios&nbsp;escreveu aos crentes da igreja que estava em &Eacute;feso. Louvamos a Deus, pois est&aacute;vamos debaixo da maldi&ccedil;&atilde;o do pecado, por&eacute;m, Cristo nos resgatou.&nbsp;Hoje, somos servos e livres para adorar ao Deus vivo. Nos aben&ccedil;oou com toda sorte de b&ecirc;n&ccedil;&atilde;os celestiais. Nos revestiu de poder, atrav&eacute;s do Esp&iacute;rito Santo, nos concedendo dons espirituais. N&atilde;o que mere&ccedil;amos, mas o seu amor nos alcan&ccedil;ou. A gra&ccedil;a nos foi dada&nbsp;por meio de Cristo Jesus:&nbsp;a gra&ccedil;a salvadora. Louve e adore o seu nome e seja sempre aben&ccedil;oado. Voc&ecirc; foi alcan&ccedil;ado por Ele e tem por direito a vida eterna em Cristo Jesus. Am&eacute;m!<br />\\r\\nTenha um dia de milagres!<br />\\r\\nAbra&ccedil;os!</p>","citation":"<p>&ldquo;Agrade&ccedil;amos ao Deus e Pai do nosso Senhor Jesus Cristo, pois ele nos tem aben&ccedil;oado por estarmos unidos com Cristo, dando-nos todos os dons espirituais do mundo celestial. Antes da cria&ccedil;&atilde;o do mundo, Deus j&aacute; nos havia escolhido para sermos dele por meio da nossa uni&atilde;o com Cristo, a fim de pertencermos somente a Deus e nos apresentarmos diante dele sem culpa. Por causa do seu amor por n&oacute;s, Deus j&aacute; havia resolvido que nos tornaria seus filhos, por meio de Jesus Cristo, pois este era o seu prazer e a sua vontade. Portanto, louvemos a Deus pela sua gloriosa gra&ccedil;a, que ele nos deu gratuitamente por meio do seu querido Filho.&rdquo;</p>","reference":"Efésios‬ ‭1:3-6‬ ‭NTLH‬‬."}