{"slug":"humildade-e-o-viver-cristao","title":"A humildade e o viver cristão","content":"<p>Bom dia, povo bendito e amado do &nbsp;Senhor Jesus. Gra&ccedil;a e paz!</p>\\r\\n\\r\\n<p>A humildade, &eacute; parte integrante de um viver crist&atilde;o. N&oacute;s precisamos aprender mais com Jesus, a ser humilde de todo nosso cora&ccedil;&atilde;o. Devemos mostrar com as nossas a&ccedil;&otilde;es, no nosso dia a dia. &nbsp;Os problemas de nossa vida, vamos entregar nas m&atilde;os do Senhor, Ele tem cuidado de n&oacute;s. Precisamos aprender a suportar os sofrimentos, pois todos os sofrimentos contribuem para o nosso fortalecimento espiritual. Creia nessa verdade. Cristo est&aacute; voltando e n&atilde;o tardar&aacute;. Se permanecermos fi&eacute;is, estaremos com Ele na Gl&oacute;ria! Creia voc&ecirc; ou n&atilde;o, Ele vem!</p>\\r\\n\\r\\n<p>Tenha um dia de milagres.</p>\\r\\n\\r\\n<p>Abra&ccedil;os.</p>","citation":"<p>&ldquo;Portanto, sejam humildes debaixo da poderosa m&atilde;o de Deus para que ele os honre no tempo certo. Entreguem todas as suas preocupa&ccedil;&otilde;es a Deus, pois ele cuida de voc&ecirc;s. Estejam alertas e fiquem vigiando porque o inimigo de voc&ecirc;s, o Diabo, anda por a&iacute; como um le&atilde;o que ruge, procurando algu&eacute;m para devorar. Fiquem firmes na f&eacute; e enfrentem o Diabo porque voc&ecirc;s sabem que no mundo inteiro os seus irm&atilde;os na f&eacute; est&atilde;o passando pelos mesmos sofrimentos. Mas, depois de sofrerem por um pouco de tempo, o Deus que tem por n&oacute;s um amor sem limites e que chamou voc&ecirc;s para tomarem parte na sua eterna gl&oacute;ria, por estarem unidos com Cristo, ele mesmo os aperfei&ccedil;oar&aacute; e dar&aacute; firmeza, for&ccedil;a e verdadeira seguran&ccedil;a. A ele seja o poder para sempre! Am&eacute;m!&rdquo;&nbsp;</p>","reference":"1 Pedro 5:6-11 NTLH"}