{"slug":"o-sangue-do-cordeiro","title":"O Sangue do Cordeiro","content":"<p>Bom dia, povo lindo do Senhor Jesus. Gra&ccedil;a e paz!<br />\\r\\nQue possamos ter um dia aben&ccedil;oado. &nbsp;Que possamos saber e entender o sacrif&iacute;cio que Cristo fez por n&oacute;s, quando deu a sua vida&nbsp;derramando o seu precioso sangue na cruz do calv&aacute;rio. Quem mais poderia fazer tal sacrif&iacute;cio, ningu&eacute;m. Somente Ele foi capaz. E me ponho a pensar, quando entro num laborat&oacute;rio para colher sangue para um exame. Vejo quantas pessoas aguardando o seu momento, posso perceber o semblante de cada rosto. Alguns confiantes, outros amedrontados, temorosos. Isso por causa de alguns ml&acute;s de sangue tirado de suas veias. &nbsp;Mas Cristo, doou todo o seu sangue em resgate de nossas vidas. Aleluia. Ent&atilde;o, a Ele devemos a honra, a gl&oacute;ria, o poder e o louvor. Ele &eacute; a nossa salva&ccedil;&atilde;o. Se voc&ecirc; ainda n&atilde;o teve um encontro com Ele, fa&ccedil;a isso agora. Como sempre digo, Ele te ama, te entende e te quer bem. Pense nisso e seja sempre vitorioso em Cristo Jesus.<br />\\r\\nTenha um lindo dia de vit&oacute;rias.<br />\\r\\nAbra&ccedil;os.</p>","citation":"<p>&ldquo;Um anjo do Senhor disse a Filipe: &ldquo;V&aacute; para o sul, para a estrada deserta que desce de Jerusal&eacute;m a Gaza&rdquo;.</p>\\r\\n\\r\\n<p>E o Esp&iacute;rito disse a Filipe: &ldquo;Aproxime-se dessa carruagem e acompanhe-a&rdquo;. Ent&atilde;o Filipe correu para a carruagem, ouviu o homem lendo o profeta Isa&iacute;as e lhe perguntou: &ldquo;O senhor entende o que est&aacute; lendo?&rdquo; Ele respondeu: &ldquo;Como posso entender se algu&eacute;m n&atilde;o me explicar?&rdquo; Assim, convidou Filipe para subir e sentar-se ao seu lado.&rdquo;<br />\\r\\n‭‭</p>","reference":"Atos‬ ‭8:26, 29-31‬ ‭NVI‬‬"}