{"slug":"obedecer-deus-em-todo-tempo","title":"Obedecer a Deus em todo tempo","content":"<p>Bom dia, na&ccedil;&atilde;o santa do Senhor Jesus. Gra&ccedil;a e paz!<br />\\r\\nObedecer, um verbo que poucos querem us&aacute;-lo. Talvez voc&ecirc; possa achar pesado essa frase, mas &eacute; uma realidade que vivemos hoje em nosso meio. Estamos vivendo um per&iacute;odo, em que muitos querem viver uma vida crist&atilde;, que satisfa&ccedil;a o seu pr&oacute;prio ego e n&atilde;o conforme o que ensina a palavra de Deus. Tudo &eacute; mais importante do que est&aacute; na presen&ccedil;a do Senhor ou do que fazer a obra do Senhor. Encontra-se espa&ccedil;o para tudo, mas n&atilde;o h&aacute; espa&ccedil;o para um compromisso com a igreja do Senhor. Est&aacute; at&eacute; parecendo que, uma vez salvo, salvo para sempre. N&atilde;o se deixe enganar, a alma que pecar, essa morrer&aacute;. Portanto, obede&ccedil;a a Palavra do Senhor, seja servo, ame o seu pr&oacute;ximo, d&ecirc; o seu tempo para o servi&ccedil;o na casa de Deus. Feito isto, certamente Deus estar&aacute; se agradando de ti, pois o amor de Deus estar&aacute; no seu cora&ccedil;&atilde;o e ser&aacute;s um crente aben&ccedil;oado e verdadeiro cidad&atilde;o dos C&eacute;us. Am&eacute;m!<br />\\r\\nTenha um dia de paz e de milagres.<br />\\r\\nAbra&ccedil;os.</p>","citation":"<p>&quot;Se obedecemos aos mandamentos de Deus, ent&atilde;o temos certeza de que o conhecemos. Se algu&eacute;m diz: &ldquo;Eu o conhe&ccedil;o&rdquo;, mas n&atilde;o obedece aos seus mandamentos, &eacute; mentiroso, e n&atilde;o h&aacute; verdade nele. Por&eacute;m, se obedecemos aos ensinamentos de Deus, sabemos que amamos a Deus de todo o nosso cora&ccedil;&atilde;o. &Eacute; assim que podemos ter certeza de que estamos vivendo unidos com Deus: Quem diz que vive unido com Deus deve viver como Jesus Cristo viveu.&quot;<br />\\r\\n&nbsp;</p>","reference":"1 João 2:3-6 NTLH"}